{
    "social": [
        {
            "name": "GitHub",
            "link": "https://github.com/pesaventofilippo",
            "icon": "fab fa-github-alt"
        },
        {
            "name": "Telegram",
            "link": "https://t.me/pesaventofilippo",
            "icon": "fab fa-telegram"
        },
        {
            "name": "Twitter",
            "link": "https://twitter.com/pesaventofil",
            "icon": "fab fa-twitter"
        },
        {
            "name": "Linkedin",
            "link": "https://linkedin.com/in/pesaventofilippo",
            "icon": "fab fa-linkedin"
        },
        {
            "name": "Instagram",
            "link": "https://instagram.com/pesaventofilippo",
            "icon": "fab fa-instagram"
        },
        {
            "name": "Sololearn",
            "link": "https://www.sololearn.com/Profile/5328477",
            "icon": "fa fa-graduation-cap"
        }
    ],

    "contactButton": {
        "text": "Like my projects?",
        "link": "https://paypal.me/pesaventofilippo",
        "icon": "fas fa-coffee"
    },

    "texts": {
        "bio": "Developer, Maker and student",
        "aboutme": "I'm a <span id='age'>18</span> year-old student. In my free time, I become a developer, producer or maker. I do pretty well at school, but I also like developing and making music.<br>My main interests are programming, cybersecurity, machine learning, networking, robotics and problem solving (I regularly participate in the Italian computer science and maths olympics - see the Achievements tab below).<br>I'm currently attending last year of high school in ITT Chilesotti, Italy.",
        "skillsBottom": "I also know other languages, but I'm not too confident with them and I don't use them very much, so they're not in this list.",
        "footer": "Made with <i class='fas fa-heart'></i> by Filippo Pesavento"
    },

    "projectPages": [
        {
            "title": "Active and/or Open-Source Projects",
            "bottomText": "I'm also working on lots of other projects that are either not open-source, archived or not available because I'm not actively developing them.<br>See <a href=\"\" onclick=\"loadProjects(1);return false;\">other projects</a> if you want to see them.",
            "projects": [
                {
                    "name": "CheColoreBot",
                    "photo": "/assets/images/projects/checolorebot.webp",
                    "description": "This bot helps you to know every morning what \"color\" your region is (in Italy, we have colors to define how much a region is under lockdown).",
                    "links": [
                        {
                            "text": "Telegram Bot",
                            "link": "https://t.me/checolorebot"
                        },
                        {
                            "text": "GitHub Repo",
                            "link": "https://github.com/pesaventofilippo/checolorebot"
                        }
                    ]
                },
                {
                    "name": "ClasseViva Bot",
                    "photo": "/assets/images/projects/classevivabot.webp",
                    "description": "This is a Telegram Bot for Spaggiari's ClasseViva school E-Register. It replaces the official app, as it implements hourly notifications about everything in the website, and daily reminders about what to do for the next day and what has been done in the morning.",
                    "links": [
                        {
                            "text": "Telegram Bot",
                            "link": "https://t.me/classevivait_bot"
                        },
                        {
                            "text": "Project Page",
                            "link": "/projects/classevivabot"
                        }
                    ]
                },
                {
                    "name": "IliadInfoBot",
                    "photo": "/assets/images/projects/iliadinfobot.webp",
                    "description": "A Telegram Bot to get all profile, SIM and contract related infos for the Italian carrier Iliad.",
                    "links": [
                        {
                            "text": "Telegram Bot",
                            "link": "https://t.me/iliadinfobot"
                        },
                        {
                            "text": "GitHub Repo",
                            "link": "https://github.com/pesaventofilippo/iliadinfobot"
                        }
                    ]
                },
                {
                    "name": "Frictionless",
                    "photo": "/assets/images/projects/frictionless.webp",
                    "description": "Frictionless is a casual Android game that I'm currently developing with Giulian Biolo. You can click below to follow the development channel and try out the game!",
                    "links": [
                        {
                            "text": "Game Website [WIP]",
                            "link": "https://frictionless.pesaventofilippo.com"
                        },
                        {
                            "text": "Follow Development",
                            "link": "https://t.me/frictionlessdev"
                        }
                    ]
                },
                {
                    "name": "OIS Ranking Bot",
                    "photo": "/assets/images/projects/oisrankingbot.webp",
                    "description": "A Telegram (and Discord too) bot to keep you updated on the leaderboard when a round of the Italian team problem-solving olympics is active.",
                    "links": [
                        {
                            "text": "Use it on Telegram!",
                            "link": "https://t.me/oisrankingbot"
                        },
                        {
                            "text": "Add it to your Discord server!",
                            "link": "https://discord.com/api/oauth2/authorize?client_id=782594209945092106&permissions=18496&scope=bot"
                        },
                        {
                            "text": "GitHub Repo",
                            "link": "https://github.com/pesaventofilippo/oisrankingbot"
                        }
                    ]
                },
                {
                    "name": "ClipShare Bot",
                    "photo": "/assets/images/projects/clipsharebot.webp",
                    "description": "A Telegram Bot to quickly paste and share text snippets. A sort of a glorified Ctrl+C and Ctrl+V, but on the cloud and with encryption.",
                    "links": [
                        {
                            "text": "Telegram Bot",
                            "link": "https://t.me/clipsharebot"
                        },
                        {
                            "text": "GitHub Repo",
                            "link": "https://github.com/pesaventofilippo/clipsharebot"
                        }
                    ]
                },
                {
                    "name": "TelepotPro",
                    "photo": "/assets/images/projects/telepotpro.webp",
                    "description": "An improved version of the Telepot Python framework by nickoala, updated to the newer APIs, with support for newer features and some bugfixes.",
                    "links": [
                        {
                            "text": "GitHub Repo",
                            "link": "https://github.com/pesaventofilippo/telepotpro"
                        }
                    ]
                },
                {
                    "name": "Free Books Bot",
                    "photo": "/assets/images/projects/freebooksbbot.webp",
                    "description": "This bot lets you find new ebooks to read by category and title. I'm constantly adding new ebooks, so it always has new content.",
                    "links": [
                        {
                            "text": "Telegram Bot",
                            "link": "https://t.me/freebooksbbot"
                        },
                        {
                            "text": "GitHub Repo",
                            "link": "https://github.com/pesaventofilippo/freebooksbbot"
                        }
                    ]
                },
                {
                    "name": "Makers AI",
                    "photo": "/assets/images/projects/makersai.webp",
                    "description": "A text-generating AI, based exclusively on messages sent in the MakersITA Telegram group, founded by overVolt. There will soon be a bot that sends generated messages in the group!",
                    "links": [
                        {
                            "text": "GitHub Repo",
                            "link": "https://github.com/pesaventofilippo/makersai"
                        },
                        {
                            "text": "MakersITA Telegram Group",
                            "link": "https://t.me/MakersITA"
                        }
                    ]
                },
                {
                    "name": "Scontino Bot",
                    "photo": "/assets/images/projects/scontino.webp",
                    "description": "This Telegram bot is made for the Telegram channel offerVolt. It can automatically format messages, add infos, retrieve a product information from the shop webpage, program posts in the future and much more. The sourcecode, starting from 1st January 2018, has become closed.",
                    "links": [
                        {
                            "text": "offerVolt Channel",
                            "link": "https://t.me/offervolt"
                        }
                    ]
                }
            ]
        },
        {
            "title": "Other Projects",
            "bottomText": "Go <a href=\"\" onclick=\"loadProjects();return false;\">back to the main page</a> for newer projects.",
            "projects": [
                {
                    "name": "TeamTrees Bot",
                    "photo": "/assets/images/projects/teamtreesbot.webp",
                    "description": "A simple Telegram Bot to keep updated with the teamtrees.org project!",
                    "links": [
                        {
                            "text": "Telegram Bot",
                            "link": "https://t.me/teamtreesbot"
                        },
                        {
                            "text": "GitHub Repo",
                            "link": "https://github.com/pesaventofilippo/teamtreesbot"
                        }
                    ]
                },
                {
                    "name": "offerVolt Bot",
                    "photo": "/assets/images/projects/offervoltbot.webp",
                    "description": "The official offerVolt channel's Telegram bot. Users of that channel can use it to talk with the staff, asking questions or suggesting products to post on the main channel.",
                    "links": [
                        {
                            "text": "Telegram Bot",
                            "link": "https://t.me/offervoltbot"
                        },
                        {
                            "text": "GitHub Repo",
                            "link": "https://github.com/pesaventofilippo/offervoltbot"
                        }
                    ]
                },
                {
                    "name": "GroupHelper Bot",
                    "photo": "/assets/images/projects/grouphelperbot.webp",
                    "description": "A Telegram bot that can help group admins to manage their groups. It has many commands, multilanguage support and a scale-type privilege for group admins, moderators and helpers.",
                    "links": [
                        {
                            "text": "GitHub Repo",
                            "link": "https://github.com/pesaventofilippo/grouphelperbot"
                        }
                    ]
                },
                {
                    "name": "Amazon Shortener Bot",
                    "photo": "/assets/images/projects/amznshortbot.webp",
                    "description": "An inline-Telegram Bot to send short Amazon URLs instead of long ones. It can just strip a link from all useless tags or fully short it using bit.ly APIs.",
                    "links": [
                        {
                            "text": "Telegram Bot",
                            "link": "https://t.me/amznshortbot"
                        },
                        {
                            "text": "GitHub Repo",
                            "link": "https://github.com/pesaventofilippo/amznshortbot"
                        }
                    ]
                },
                {
                    "name": "Monolix",
                    "photo": "/assets/images/projects/monolix.webp",
                    "description": "Monolix is a startup Software House, founded by Gianluca Parri, Emanuele Lillo and me in 2018. It has many projects on its GitHub page, including the most famous one, Banklog.",
                    "links": [
                        {
                            "text": "GitHub Page",
                            "link": "https://github.com/monolix"
                        }
                    ]
                },
                {
                    "name": "Geometry Dash Bot",
                    "photo": "/assets/images/projects/geometrydashbot.webp",
                    "description": "A Telegram Bot that lets you see many GD stats, levels, info and more, using GD Colon's Web APIs!",
                    "links": [
                        {
                            "text": "Telegram Bot",
                            "link": "https://t.me/geometrydashbot"
                        },
                        {
                            "text": "GitHub Repo",
                            "link": "https://github.com/pesaventofilippo/geometrydashbot"
                        }
                    ]
                },
                {
                    "name": "SpotiPyBot",
                    "photo": "/assets/images/projects/spotipybot.webp",
                    "description": "A CLI automated bot that uses Google Chrome drivers to generate automatic Spotify listens on a given playlist.",
                    "links": [
                        {
                            "text": "GitHub Repo",
                            "link": "https://github.com/pesaventofilippo/spotipybot"
                        }
                    ]
                }
            ]
        }
    ],

    "contactInfo": [
        {
            "name": "Location",
            "text": "Vicenza, IT",
            "icon": "fas fa-map-marker-alt"
        },
        {
            "name": "Personal Email",
            "text": "hello[at]pesaventofilippo.com",
            "icon": "fas fa-envelope"
        },
        {
            "name": "Personal Email",
            "text": "pesaventofilippo[at]gmail.com",
            "icon": "fas fa-envelope"
        },
        {
            "name": "School Email",
            "text": "fpesavento[at]chilesotti.it",
            "icon": "fas fa-envelope"
        },
        {
            "name": "Birthday",
            "text": "23/06/2003",
            "icon": "fas fa-birthday-cake"
        }
    ],

    "skills": [
        {
            "title": "Git",
            "level": "High",
            "score": 4
        },
        {
            "title": "Bash / Linux Terminal",
            "level": "High",
            "score": 3.5
        },
        {
            "title": "Networking",
            "level": "High",
            "score": 3
        },
        {
            "title": "Machine Learning / AI",
            "level": "Medium",
            "score": 2.5
        },
        {
            "title": "Docker",
            "level": "Low",
            "score": 2
        },
        {
            "title": "Python",
            "level": "Expert",
            "score": 5
        },
        {
            "title": "C#",
            "level": "High",
            "score": 4
        },
        {
            "title": "C++",
            "level": "Medium",
            "score": 3
        },
        {
            "title": "JavaScript",
            "level": "Medium",
            "score": 2.5
        },
        {
            "title": "HTML/CSS",
            "level": "Medium",
            "score": 2.5
        },
        {
            "title": "Java",
            "level": "Low",
            "score": 2
        },
        {
            "title": "PHP",
            "level": "Low",
            "score": 1.5
        }
    ],

    "languages": [
        {
            "title": "Italian",
            "level": "Native Speaker",
            "score": 5
        },
        {
            "title": "English",
            "level": "Medium/High (B2)",
            "score": 3.5
        }
    ],

    "education": [
        {
            "title": "Mid School Diploma (10+/10)",
            "description": "G. Ciscato Mid School",
            "year": "2014-2017",
            "icon": "fas fa-graduation-cap"
        },
        {
            "title": "CS Student",
            "description": "ITT G. Chilesotti",
            "year": "2017-Present",
            "icon": "fas fa-graduation-cap"
        }
    ],

    "achievements": [
        {
            "title": "ViChallenge Hackathon",
            "description": "<a href=\"https://digitalinnovationhubvicenza.it/vi-challenge-hackathon-27-e-28-novembre-2021\">Best project - 1st Place (team)</a>",
            "year": "2021",
            "icon": "fas fa-comments"
        },
        {
            "title": "OII Finals",
            "description": "National Coding finals - 86th in Italy",
            "year": "2021",
            "icon": "fas fa-code"
        },
        {
            "title": "OIS Finals",
            "description": "National Coding finals (teams) - 4th in Italy",
            "year": "2021",
            "icon": "fas fa-code"
        },
        {
            "title": "Bocconi Math Finals",
            "description": "National Maths finals (L1) - 94th in Italy",
            "year": "2021",
            "icon": "fas fa-trophy"
        },
        {
            "title": "Bocconi Math Finals",
            "description": "National Maths finals (C1) - 283rd in Italy",
            "year": "2016",
            "icon": "fas fa-trophy"
        }
    ],

    "work": [
        {
            "title": "IT Stage - 1 month",
            "description": "<a href=\"https://www.advnet.it\" target=\"_blank\">ADVNET Srl</a>",
            "year": "03/06/21 - 30/06/21",
            "icon": "fas fa-briefcase"
        }
    ]
}
